apex/__init__.py
apex/RNN/RNNBackend.py
apex/RNN/__init__.py
apex/RNN/cells.py
apex/RNN/models.py
apex/amp/__init__.py
apex/amp/__version__.py
apex/amp/_amp_state.py
apex/amp/_initialize.py
apex/amp/_process_optimizer.py
apex/amp/amp.py
apex/amp/compat.py
apex/amp/frontend.py
apex/amp/handle.py
apex/amp/opt.py
apex/amp/rnn_compat.py
apex/amp/scaler.py
apex/amp/utils.py
apex/amp/wrap.py
apex/amp/lists/__init__.py
apex/amp/lists/functional_overrides.py
apex/amp/lists/tensor_overrides.py
apex/amp/lists/torch_overrides.py
apex/contrib/__init__.py
apex/contrib/bottleneck/__init__.py
apex/contrib/bottleneck/bottleneck.py
apex/contrib/bottleneck/bottleneck_module_test.py
apex/contrib/bottleneck/test.py
apex/contrib/fmha/__init__.py
apex/contrib/fmha/fmha.py
apex/contrib/groupbn/__init__.py
apex/contrib/groupbn/batch_norm.py
apex/contrib/layer_norm/__init__.py
apex/contrib/layer_norm/layer_norm.py
apex/contrib/multihead_attn/__init__.py
apex/contrib/multihead_attn/encdec_multihead_attn.py
apex/contrib/multihead_attn/encdec_multihead_attn_func.py
apex/contrib/multihead_attn/fast_encdec_multihead_attn_func.py
apex/contrib/multihead_attn/fast_encdec_multihead_attn_norm_add_func.py
apex/contrib/multihead_attn/fast_self_multihead_attn_func.py
apex/contrib/multihead_attn/fast_self_multihead_attn_norm_add_func.py
apex/contrib/multihead_attn/mask_softmax_dropout_func.py
apex/contrib/multihead_attn/self_multihead_attn.py
apex/contrib/multihead_attn/self_multihead_attn_func.py
apex/contrib/optimizers/__init__.py
apex/contrib/optimizers/distributed_fused_adam.py
apex/contrib/optimizers/distributed_fused_adam_v2.py
apex/contrib/optimizers/distributed_fused_adam_v3.py
apex/contrib/optimizers/distributed_fused_lamb.py
apex/contrib/optimizers/fp16_optimizer.py
apex/contrib/optimizers/fused_adam.py
apex/contrib/optimizers/fused_lamb.py
apex/contrib/optimizers/fused_sgd.py
apex/contrib/sparsity/__init__.py
apex/contrib/sparsity/asp.py
apex/contrib/sparsity/sparse_masklib.py
pytorch_extension-0.2.dist-info/LICENSE
pytorch_extension-0.2.dist-info/METADATA
pytorch_extension-0.2.dist-info/WHEEL
pytorch_extension-0.2.dist-info/top_level.txt
pytorch_extension-0.2.dist-info/RECORD
