Metadata-Version: 2.1
Name: pytorch-extension
Version: 0.2
Summary: Package for A PyTorch Extension by NVIDIA
Home-page: https://github.com/artitw/apex
Author: Artit Wangperawong
Author-email: artitw@gmail.com
License: UNKNOWN
Keywords: artificial intelligence pytorch data science deep machine learning
Platform: UNKNOWN
License-File: LICENSE
